pytorch_wavelets/__init__.py
pytorch_wavelets/_version.py
pytorch_wavelets/utils.py
pytorch_wavelets/dtcwt/__init__.py
pytorch_wavelets/dtcwt/coeffs.py
pytorch_wavelets/dtcwt/lowlevel.py
pytorch_wavelets/dtcwt/lowlevel2.py
pytorch_wavelets/dtcwt/transform2d.py
pytorch_wavelets/dtcwt/transform_funcs.py
pytorch_wavelets/dtcwt/data/__init__.py
pytorch_wavelets/dtcwt/data/antonini.npz
pytorch_wavelets/dtcwt/data/farras.npz
pytorch_wavelets/dtcwt/data/legall.npz
pytorch_wavelets/dtcwt/data/near_sym_a.npz
pytorch_wavelets/dtcwt/data/near_sym_a2.npz
pytorch_wavelets/dtcwt/data/near_sym_b.npz
pytorch_wavelets/dtcwt/data/near_sym_b_bp.npz
pytorch_wavelets/dtcwt/data/qshift_06.npz
pytorch_wavelets/dtcwt/data/qshift_32.npz
pytorch_wavelets/dtcwt/data/qshift_a.npz
pytorch_wavelets/dtcwt/data/qshift_b.npz
pytorch_wavelets/dtcwt/data/qshift_b_bp.npz
pytorch_wavelets/dtcwt/data/qshift_c.npz
pytorch_wavelets/dtcwt/data/qshift_d.npz
pytorch_wavelets/dwt/__init__.py
pytorch_wavelets/dwt/lowlevel.py
pytorch_wavelets/dwt/swt_inverse.py
pytorch_wavelets/dwt/transform1d.py
pytorch_wavelets/dwt/transform2d.py
pytorch_wavelets/scatternet/__init__.py
pytorch_wavelets/scatternet/layers.py
pytorch_wavelets/scatternet/lowlevel.py
pytorch_wavelets-1.3.0.dist-info/LICENSE
pytorch_wavelets-1.3.0.dist-info/METADATA
pytorch_wavelets-1.3.0.dist-info/WHEEL
pytorch_wavelets-1.3.0.dist-info/top_level.txt
pytorch_wavelets-1.3.0.dist-info/RECORD
