Metadata-Version: 2.1
Name: pytorch_wavelets
Version: 1.3.0
Summary: A port of the DTCWT toolbox to run on pytorch
Home-page: https://github.com/fbcotter/pytorch_wavelets
Author: Fergal Cotter
Author-email: fbc23@cam.ac.uk
License: Free To Use
Keywords: pytorch,DWT,DTCWT,wavelet,complex wavelet
Classifier: Development Status :: 3 - Alpha
Classifier: License :: Free To Use But Restricted
Classifier: Programming Language :: Python :: 3
Provides-Extra: docs
License-File: LICENSE
